uniprotu/__init__.py
uniprotu/py.typed
uniprotu/rest_api_utils.py
uniprotu/uniprot_utils.py
uniprotu-0.1.3.dist-info/METADATA
uniprotu-0.1.3.dist-info/WHEEL
uniprotu-0.1.3.dist-info/licenses/LICENSE
uniprotu-0.1.3.dist-info/RECORD
