Metadata-Version: 2.3
Name: uniprotu
Version: 0.1.3
Summary: UniProt utils.
Author-email: yoramzarai <yoram.zarai@gmail.com>
Classifier: Intended Audience :: Science/Research
Classifier: License :: OSI Approved :: MIT License
Classifier: Operating System :: OS Independent
Classifier: Programming Language :: Python :: 3.10
Classifier: Topic :: Scientific/Engineering :: Bio-Informatics
Requires-Python: >=3.10
Requires-Dist: pandas>=2.2.3
Requires-Dist: requests>=2.32.3
